{
  "tests": {
    "id": "ACES-011",
    "title": "Search by Quote Number",
    "description": "Search by quote number",
    "feature": "ACES Policy Search",
    "story": "Search ACES Policies",
    "severity": "NORMAL",
    "tag": [
      "regression"
    ],
    "data": {
      "payload": {
        "company": 2,
        "quoteNumber": 15749598
      },
      "expected_results": [
        {
          "policyNumber": "01APM04992001",
          "quoteNumber": 15749598,
          "insuredName": "BRONWYNS OASIS, LLC",
          "dba": "",
          "firstName": "",
          "lastName": "",
          "effectiveDate": "2024-08-01T10:03:09",
          "source": "ACES",
          "agencyCode": "N26300",
          "agencyName": "Berkshire Hathaway Homestate Companies",
          "policyState": "AZ"
        }
      ]
    }
  }
}